src/chat_models/base.py
src/chat_models/chatgpt.py
src/chat_models/gemini.py
src/chat_models/gemini_patch.py
src/fis_config.py
src/fis_tool.py
src/interactive_main.py
src/interactive_prj.py
src/itv_flow.py
src/options/base.py
src/options/choices.py
src/prj_forge.py
src/setting.py
src/utils.py
fis_tool-0.4.0.dist-info/LICENSE
fis_tool-0.4.0.dist-info/METADATA
fis_tool-0.4.0.dist-info/WHEEL
fis_tool-0.4.0.dist-info/entry_points.txt
fis_tool-0.4.0.dist-info/RECORD
