Metadata-Version: 2.1
Name: fis-tool
Version: 0.4.0
Summary: FIS (File Interaction Script) 工具，用于生成、读取和应用项目文件结构描述，方便与 LLM 进行交互，实现高效的代码变更。
Author: KroMiose
Author-email: li_xiangff@163.com
Requires-Python: >=3.9,<3.13
Classifier: Programming Language :: Python :: 3
Classifier: Programming Language :: Python :: 3.9
Classifier: Programming Language :: Python :: 3.10
Classifier: Programming Language :: Python :: 3.11
Classifier: Programming Language :: Python :: 3.12
Requires-Dist: argparse (>=1.4.0,<2.0.0)
Requires-Dist: gitignorefile (>=1.1.2,<2.0.0)
Requires-Dist: google-generativeai (>=0.6.0,<0.7.0)
Requires-Dist: inquirer (>=3.2.4,<4.0.0)
Requires-Dist: keyboard (>=0.13.5,<0.14.0)
Requires-Dist: openai (>=1.34.0,<2.0.0)
Requires-Dist: pyyaml (>=6.0.1,<7.0.0)
